filelock/__init__.py
filelock/_api.py
filelock/_error.py
filelock/_soft.py
filelock/_unix.py
filelock/_util.py
filelock/_windows.py
filelock/version.py
filelock_lts_py37/__init__.py
filelock_lts_py37/_api.py
filelock_lts_py37/_error.py
filelock_lts_py37/_soft.py
filelock_lts_py37/_unix.py
filelock_lts_py37/_util.py
filelock_lts_py37/_windows.py
filelock_lts_py37/version.py
filelock_lts_py37-2025.68146.2.dist-info/METADATA
filelock_lts_py37-2025.68146.2.dist-info/WHEEL
filelock_lts_py37-2025.68146.2.dist-info/top_level.txt
filelock_lts_py37-2025.68146.2.dist-info/RECORD
