Metadata-Version: 2.1
Name: filelock-lts-py37
Version: 2025.68146.2
Summary: Python 3.7 filelock with CVE-2025-68146 security patch (symlink attack prevention via O_NOFOLLOW)
License: Unlicense
Project-URL: Homepage, https://github.com/1minds3t/filelock-lts
Project-URL: CVE Details, https://nvd.nist.gov/vuln/detail/CVE-2025-68146
Project-URL: Source, https://github.com/1minds3t/filelock-lts/tree/py3.7
Classifier: Programming Language :: Python :: 3.7
Classifier: Topic :: Security
Classifier: Intended Audience :: Developers
Requires-Python: <3.8,>=3.7
